udacity_distributions_5_exe/Binomialdistribution.py
udacity_distributions_5_exe/Gaussiandistribution.py
udacity_distributions_5_exe/Generaldistribution.py
udacity_distributions_5_exe/__init__.py
udacity_distributions_5_exe-0.1.dist-info/DESCRIPTION.rst
udacity_distributions_5_exe-0.1.dist-info/METADATA
udacity_distributions_5_exe-0.1.dist-info/RECORD
udacity_distributions_5_exe-0.1.dist-info/WHEEL
udacity_distributions_5_exe-0.1.dist-info/metadata.json
udacity_distributions_5_exe-0.1.dist-info/top_level.txt
