Metadata-Version: 2.0
Name: udacity-distributions-5-exe
Version: 0.1
Summary: Gaussian distributions
Home-page: UNKNOWN
Author: UNKNOWN
Author-email: UNKNOWN
License: UNKNOWN
Platform: UNKNOWN
